CHANGES.rst
LICENSE
MANIFEST.in
README.rst
setup.py
matchtpl/__init__.py
matchtpl/core.py
matchtpl.egg-info/PKG-INFO
matchtpl.egg-info/SOURCES.txt
matchtpl.egg-info/dependency_links.txt
matchtpl.egg-info/entry_points.txt
matchtpl.egg-info/requires.txt
matchtpl.egg-info/top_level.txt
test/amazon.bat
test/amazon.html
test/amazon.sh
test/amazon.xml
test/demo.bat
test/demo.html
test/demo.sh
test/demo.xml
test/demo_xml.bat
test/demo_xml.sh
test/demo_xml.xml
test/stream.py
test/weather_yahoo.bat
test/weather_yahoo.sh
test/weather_yahoo.xml