Metadata-Version: 1.1
Name: matchtpl
Version: 0.1.2
Summary: Matching template to extract data from xml or html
Home-page: https://github.com/bolitt/py-matchtpl.git
Author: Tian L.
Author-email: bolitt@gmail.com
License: BSD license
Keywords: match template crawler extract data xml html
Platform: UNKNOWN
Classifier: Programming Language :: Python
Classifier: Programming Language :: Python :: 2
Classifier: Programming Language :: Python :: 2.6
Classifier: Programming Language :: Python :: 2.7
Classifier: Intended Audience :: Developers
Classifier: Intended Audience :: Science/Research
Classifier: License :: OSI Approved :: BSD License
Classifier: Operating System :: OS Independent
Classifier: Topic :: Software Development
Classifier: Topic :: Software Development :: Libraries :: Python Modules
